Workbook

Sheet Executive Dashboard
A1: Total Revenue YTD | B1: 38505
A2: Gross Profit Margin | B2: 1
A3: Net Income YTD | B3: 31655
A4: Current Cash Balance | B4: 5430
A5: Accounts Receivable | B5: 33075
A6: Monthly Recurring Revenue Target (June 2027) | B6: 62000
A7: Total Tracked Submissions | B7: 267
A8: Annual Financial Comparison & Forecast
A9: Metric | B9: 2026 (Actual + Forecast) | C9: 2027 (Forecast) | D9: YoY Growth
A10: Total Revenue | B10: 151605 | C10: 1080000 | D10: +612.4%
A11: Gross Profit | B11: 151605 | C11: 1080000 | D11: +612.4%
A12: Operating Expenses | B12: 10000 | C12: 60000 | D12: +500.0%
A13: EBITDA | B13: 141605 | C13: 1020000 | D13: +620.3%
A14: Net Income | B14: 141605 | C14: 1020000 | D14: +620.3%

Sheet Income Statement
A1: Category | B1: 46023 | C1: 46054 | D1: 46082 | E1: 46113 | F1: 46143 | G1: 46174 | H1: 46204 | I1: 46235 | J1: 46266 | K1: 46296 | L1: 46327 | M1: 46357 | N1: 2026 Total | O1: 46388 | P1: 46419 | Q1: 46447 | R1: 46478 | S1: 46508 | T1: 46539 | U1: 46569 | V1: 46600 | W1: 46631 | X1: 46661 | Y1: 46692 | Z1: 46722 | AA1: 2027 Total
A2: Revenue
A3: Public Bounties | B3: =IF(B$1="2026 Total", SUM($B3:M3), IF(B$1="2027 Total", SUM($O3:Z3), SUMIFS('Transaction Ledger'!$G:$G, 'Transaction Ledger'!$H:$H, "Bounty Revenue", 'Transaction Ledger'!$A:$A, ">="&B$1, 'Transaction Ledger'!$A:$A, "<="&EOMONTH(B$1,0)))) | C3: =IF(C$1="2026 Total", SUM($B3:N3), IF(C$1="2027 Total", SUM($O3:AA3), SUMIFS('Transaction Ledger'!$G:$G, 'Transaction Ledger'!$H:$H, "Bounty Revenue", 'Transaction Ledger'!$A:$A, ">="&C$1, 'Transaction Ledger'!$A:$A, "<="&EOMONTH(C$1,0)))) | D3: =IF(D$1="2026 Total", SUM($B3:O3), IF(D$1="2027 Total", SUM($O3:AB3), SUMIFS('Transaction Ledger'!$G:$G, 'Transaction Ledger'!$H:$H, "Bounty Revenue", 'Transaction Ledger'!$A:$A, ">="&D$1, 'Transaction Ledger'!$A:$A, "<="&EOMONTH(D$1,0)))) | E3: =IF(E$1="2026 Total", SUM($B3:P3), IF(E$1="2027 Total", SUM($O3:AC3), SUMIFS('Transaction Ledger'!$G:$G, 'Transaction Ledger'!$H:$H, "Bounty Revenue", 'Transaction Ledger'!$A:$A, ">="&E$1, 'Transaction Ledger'!$A:$A, "<="&EOMONTH(E$1,0)))) | F3: =IF(F$1="2026 Total", SUM($B3:Q3), IF(F$1="2027 Total", SUM($O3:AD3), SUMIFS('Transaction Ledger'!$G:$G, 'Transaction Ledger'!$H:$H, "Bounty Revenue", 'Transaction Ledger'!$A:$A, ">="&F$1, 'Transaction Ledger'!$A:$A, "<="&EOMONTH(F$1,0)))) | G3: =IF(G$1="2026 Total", SUM($B3:R3), IF(G$1="2027 Total", SUM($O3:AE3), SUMIFS('Transaction Ledger'!$G:$G, 'Transaction Ledger'!$H:$H, "Bounty Revenue", 'Transaction Ledger'!$A:$A, ">="&G$1, 'Transaction Ledger'!$A:$A, "<="&EOMONTH(G$1,0)))) | H3: =IF(H$1="2026 Total", SUM($B3:S3), IF(H$1="2027 Total", SUM($O3:AF3), SUMIFS('Transaction Ledger'!$G:$G, 'Transaction Ledger'!$H:$H, "Bounty Revenue", 'Transaction Ledger'!$A:$A, ">="&H$1, 'Transaction Ledger'!$A:$A, "<="&EOMONTH(H$1,0)))) | I3: 27205 | J3: 22000 | K3: 26000 | L3: 28000 | M3: 30000 | N3: 116605 | O3: 32000 | P3: 34000 | Q3: 35000 | R3: 36000 | S3: 37000 | T3: 38000 | U3: 38000 | V3: 38000 | W3: 38000 | X3: 38000 | Y3: 38000 | Z3: 38000 | AA3: 440000
A4: Codebase Maintenance Retainers | B4: =IF(B$1="2026 Total", SUM($B3:M3), IF(B$1="2027 Total", SUM($O3:Z3), SUMIFS('Transaction Ledger'!$G:$G, 'Transaction Ledger'!$H:$H, "Retainer Revenue", 'Transaction Ledger'!$A:$A, ">="&B$1, 'Transaction Ledger'!$A:$A, "<="&EOMONTH(B$1,0)))) | C4: =IF(C$1="2026 Total", SUM($B3:N3), IF(C$1="2027 Total", SUM($O3:AA3), SUMIFS('Transaction Ledger'!$G:$G, 'Transaction Ledger'!$H:$H, "Retainer Revenue", 'Transaction Ledger'!$A:$A, ">="&C$1, 'Transaction Ledger'!$A:$A, "<="&EOMONTH(C$1,0)))) | D4: =IF(D$1="2026 Total", SUM($B3:O3), IF(D$1="2027 Total", SUM($O3:AB3), SUMIFS('Transaction Ledger'!$G:$G, 'Transaction Ledger'!$H:$H, "Retainer Revenue", 'Transaction Ledger'!$A:$A, ">="&D$1, 'Transaction Ledger'!$A:$A, "<="&EOMONTH(D$1,0)))) | E4: =IF(E$1="2026 Total", SUM($B3:P3), IF(E$1="2027 Total", SUM($O3:AC3), SUMIFS('Transaction Ledger'!$G:$G, 'Transaction Ledger'!$H:$H, "Retainer Revenue", 'Transaction Ledger'!$A:$A, ">="&E$1, 'Transaction Ledger'!$A:$A, "<="&EOMONTH(E$1,0)))) | F4: =IF(F$1="2026 Total", SUM($B3:Q3), IF(F$1="2027 Total", SUM($O3:AD3), SUMIFS('Transaction Ledger'!$G:$G, 'Transaction Ledger'!$H:$H, "Retainer Revenue", 'Transaction Ledger'!$A:$A, ">="&F$1, 'Transaction Ledger'!$A:$A, "<="&EOMONTH(F$1,0)))) | G4: =IF(G$1="2026 Total", SUM($B3:R3), IF(G$1="2027 Total", SUM($O3:AE3), SUMIFS('Transaction Ledger'!$G:$G, 'Transaction Ledger'!$H:$H, "Retainer Revenue", 'Transaction Ledger'!$A:$A, ">="&G$1, 'Transaction Ledger'!$A:$A, "<="&EOMONTH(G$1,0)))) | H4: =IF(H$1="2026 Total", SUM($B3:S3), IF(H$1="2027 Total", SUM($O3:AF3), SUMIFS('Transaction Ledger'!$G:$G, 'Transaction Ledger'!$H:$H, "Retainer Revenue", 'Transaction Ledger'!$A:$A, ">="&H$1, 'Transaction Ledger'!$A:$A, "<="&EOMONTH(H$1,0)))) | I4: 0 | J4: =IF(J$1="2026 Total", SUM($B3:U3), IF(J$1="2027 Total", SUM($O3:AH3), SUMIFS('Transaction Ledger'!$G:$G, 'Transaction Ledger'!$H:$H, "Retainer Revenue", 'Transaction Ledger'!$A:$A, ">="&J$1, 'Transaction Ledger'!$A:$A, "<="&EOMONTH(J$1,0)))) | K4: 5000 | L4: 12000 | M4: 18000 | N4: 35000 | O4: 25000 | P4: 33000 | Q4: 42000 | R4: 50000 | S4: 56000 | T4: 62000 | U4: 62000 | V4: 62000 | W4: 62000 | X4: 62000 | Y4: 62000 | Z4: 62000 | AA4: 640000
A5: Product Sprints | B5: =IF(B$1="2026 Total", SUM($B3:M3), IF(B$1="2027 Total", SUM($O3:Z3), SUMIFS('Transaction Ledger'!$G:$G, 'Transaction Ledger'!$H:$H, "Product Sprints", 'Transaction Ledger'!$A:$A, ">="&B$1, 'Transaction Ledger'!$A:$A, "<="&EOMONTH(B$1,0)))) | C5: =IF(C$1="2026 Total", SUM($B3:N3), IF(C$1="2027 Total", SUM($O3:AA3), SUMIFS('Transaction Ledger'!$G:$G, 'Transaction Ledger'!$H:$H, "Product Sprints", 'Transaction Ledger'!$A:$A, ">="&C$1, 'Transaction Ledger'!$A:$A, "<="&EOMONTH(C$1,0)))) | D5: =IF(D$1="2026 Total", SUM($B3:O3), IF(D$1="2027 Total", SUM($O3:AB3), SUMIFS('Transaction Ledger'!$G:$G, 'Transaction Ledger'!$H:$H, "Product Sprints", 'Transaction Ledger'!$A:$A, ">="&D$1, 'Transaction Ledger'!$A:$A, "<="&EOMONTH(D$1,0)))) | E5: =IF(E$1="2026 Total", SUM($B3:P3), IF(E$1="2027 Total", SUM($O3:AC3), SUMIFS('Transaction Ledger'!$G:$G, 'Transaction Ledger'!$H:$H, "Product Sprints", 'Transaction Ledger'!$A:$A, ">="&E$1, 'Transaction Ledger'!$A:$A, "<="&EOMONTH(E$1,0)))) | F5: =IF(F$1="2026 Total", SUM($B3:Q3), IF(F$1="2027 Total", SUM($O3:AD3), SUMIFS('Transaction Ledger'!$G:$G, 'Transaction Ledger'!$H:$H, "Product Sprints", 'Transaction Ledger'!$A:$A, ">="&F$1, 'Transaction Ledger'!$A:$A, "<="&EOMONTH(F$1,0)))) | G5: =IF(G$1="2026 Total", SUM($B3:R3), IF(G$1="2027 Total", SUM($O3:AE3), SUMIFS('Transaction Ledger'!$G:$G, 'Transaction Ledger'!$H:$H, "Product Sprints", 'Transaction Ledger'!$A:$A, ">="&G$1, 'Transaction Ledger'!$A:$A, "<="&EOMONTH(G$1,0)))) | H5: =IF(H$1="2026 Total", SUM($B3:S3), IF(H$1="2027 Total", SUM($O3:AF3), SUMIFS('Transaction Ledger'!$G:$G, 'Transaction Ledger'!$H:$H, "Product Sprints", 'Transaction Ledger'!$A:$A, ">="&H$1, 'Transaction Ledger'!$A:$A, "<="&EOMONTH(H$1,0)))) | I5: 0 | J5: =IF(J$1="2026 Total", SUM($B3:U3), IF(J$1="2027 Total", SUM($O3:AH3), SUMIFS('Transaction Ledger'!$G:$G, 'Transaction Ledger'!$H:$H, "Product Sprints", 'Transaction Ledger'!$A:$A, ">="&J$1, 'Transaction Ledger'!$A:$A, "<="&EOMONTH(J$1,0)))) | K5: =IF(K$1="2026 Total", SUM($B3:V3), IF(K$1="2027 Total", SUM($O3:AI3), SUMIFS('Transaction Ledger'!$G:$G, 'Transaction Ledger'!$H:$H, "Product Sprints", 'Transaction Ledger'!$A:$A, ">="&K$1, 'Transaction Ledger'!$A:$A, "<="&EOMONTH(K$1,0)))) | L5: =IF(L$1="2026 Total", SUM($B3:W3), IF(L$1="2027 Total", SUM($O3:AJ3), SUMIFS('Transaction Ledger'!$G:$G, 'Transaction Ledger'!$H:$H, "Product Sprints", 'Transaction Ledger'!$A:$A, ">="&L$1, 'Transaction Ledger'!$A:$A, "<="&EOMONTH(L$1,0)))) | M5: =IF(M$1="2026 Total", SUM($B3:X3), IF(M$1="2027 Total", SUM($O3:AK3), SUMIFS('Transaction Ledger'!$G:$G, 'Transaction Ledger'!$H:$H, "Product Sprints", 'Transaction Ledger'!$A:$A, ">="&M$1, 'Transaction Ledger'!$A:$A, "<="&EOMONTH(M$1,0)))) | N5: =SUM(B5:M5) | O5: =IF(O$1="2026 Total", SUM($B3:Z3), IF(O$1="2027 Total", SUM($O3:AM3), SUMIFS('Transaction Ledger'!$G:$G, 'Transaction Ledger'!$H:$H, "Product Sprints", 'Transaction Ledger'!$A:$A, ">="&O$1, 'Transaction Ledger'!$A:$A, "<="&EOMONTH(O$1,0)))) | P5: =IF(P$1="2026 Total", SUM($B3:AA3), IF(P$1="2027 Total", SUM($O3:AN3), SUMIFS('Transaction Ledger'!$G:$G, 'Transaction Ledger'!$H:$H, "Product Sprints", 'Transaction Ledger'!$A:$A, ">="&P$1, 'Transaction Ledger'!$A:$A, "<="&EOMONTH(P$1,0)))) | Q5: =IF(Q$1="2026 Total", SUM($B3:AB3), IF(Q$1="2027 Total", SUM($O3:AO3), SUMIFS('Transaction Ledger'!$G:$G, 'Transaction Ledger'!$H:$H, "Product Sprints", 'Transaction Ledger'!$A:$A, ">="&Q$1, 'Transaction Ledger'!$A:$A, "<="&EOMONTH(Q$1,0)))) | R5: =IF(R$1="2026 Total", SUM($B3:AC3), IF(R$1="2027 Total", SUM($O3:AP3), SUMIFS('Transaction Ledger'!$G:$G, 'Transaction Ledger'!$H:$H, "Product Sprints", 'Transaction Ledger'!$A:$A, ">="&R$1, 'Transaction Ledger'!$A:$A, "<="&EOMONTH(R$1,0)))) | S5: =IF(S$1="2026 Total", SUM($B3:AD3), IF(S$1="2027 Total", SUM($O3:AQ3), SUMIFS('Transaction Ledger'!$G:$G, 'Transaction Ledger'!$H:$H, "Product Sprints", 'Transaction Ledger'!$A:$A, ">="&S$1, 'Transaction Ledger'!$A:$A, "<="&EOMONTH(S$1,0)))) | T5: =IF(T$1="2026 Total", SUM($B3:AE3), IF(T$1="2027 Total", SUM($O3:AR3), SUMIFS('Transaction Ledger'!$G:$G, 'Transaction Ledger'!$H:$H, "Product Sprints", 'Transaction Ledger'!$A:$A, ">="&T$1, 'Transaction Ledger'!$A:$A, "<="&EOMONTH(T$1,0)))) | U5: =IF(U$1="2026 Total", SUM($B3:AF3), IF(U$1="2027 Total", SUM($O3:AS3), SUMIFS('Transaction Ledger'!$G:$G, 'Transaction Ledger'!$H:$H, "Product Sprints", 'Transaction Ledger'!$A:$A, ">="&U$1, 'Transaction Ledger'!$A:$A, "<="&EOMONTH(U$1,0)))) | V5: =IF(V$1="2026 Total", SUM($B3:AG3), IF(V$1="2027 Total", SUM($O3:AT3), SUMIFS('Transaction Ledger'!$G:$G, 'Transaction Ledger'!$H:$H, "Product Sprints", 'Transaction Ledger'!$A:$A, ">="&V$1, 'Transaction Ledger'!$A:$A, "<="&EOMONTH(V$1,0)))) | ... Z5: =IF(Z$1="2026 Total", SUM($B3:AK3), IF(Z$1="2027 Total", SUM($O3:AX3), SUMIFS('Transaction Ledger'!$G:$G, 'Transaction Ledger'!$H:$H, "Product Sprints", 'Transaction Ledger'!$A:$A, ">="&Z$1, 'Transaction Ledger'!$A:$A, "<="&EOMONTH(Z$1,0)))) | AA5: =SUM(O5:Z5)
A6: Total Revenue | B6: =SUM(B3:B5) | C6: =SUM(C3:C5) | D6: =SUM(D3:D5) | E6: =SUM(E3:E5) | F6: =SUM(F3:F5) | G6: =SUM(G3:G5) | H6: =SUM(H3:H5) | I6: 27205 | J6: 22000 | K6: 31000 | L6: 40000 | M6: 48000 | N6: 151605 | O6: 57000 | P6: 67000 | Q6: 77000 | R6: 86000 | S6: 93000 | T6: 100000 | U6: 100000 | V6: 100000 | W6: 100000 | X6: 100000 | Y6: 100000 | Z6: 100000 | AA6: 1080000
A7: Cost of Goods Sold
A8: Compute & Hosting | B8: =IF(B$1="2026 Total", SUM($B3:M3), IF(B$1="2027 Total", SUM($O3:Z3), SUMIFS('Transaction Ledger'!$G:$G, 'Transaction Ledger'!$H:$H, "Compute/API Expense", 'Transaction Ledger'!$A:$A, ">="&B$1, 'Transaction Ledger'!$A:$A, "<="&EOMONTH(B$1,0)))) | C8: =IF(C$1="2026 Total", SUM($B3:N3), IF(C$1="2027 Total", SUM($O3:AA3), SUMIFS('Transaction Ledger'!$G:$G, 'Transaction Ledger'!$H:$H, "Compute/API Expense", 'Transaction Ledger'!$A:$A, ">="&C$1, 'Transaction Ledger'!$A:$A, "<="&EOMONTH(C$1,0)))) | D8: =IF(D$1="2026 Total", SUM($B3:O3), IF(D$1="2027 Total", SUM($O3:AB3), SUMIFS('Transaction Ledger'!$G:$G, 'Transaction Ledger'!$H:$H, "Compute/API Expense", 'Transaction Ledger'!$A:$A, ">="&D$1, 'Transaction Ledger'!$A:$A, "<="&EOMONTH(D$1,0)))) | E8: =IF(E$1="2026 Total", SUM($B3:P3), IF(E$1="2027 Total", SUM($O3:AC3), SUMIFS('Transaction Ledger'!$G:$G, 'Transaction Ledger'!$H:$H, "Compute/API Expense", 'Transaction Ledger'!$A:$A, ">="&E$1, 'Transaction Ledger'!$A:$A, "<="&EOMONTH(E$1,0)))) | F8: =IF(F$1="2026 Total", SUM($B3:Q3), IF(F$1="2027 Total", SUM($O3:AD3), SUMIFS('Transaction Ledger'!$G:$G, 'Transaction Ledger'!$H:$H, "Compute/API Expense", 'Transaction Ledger'!$A:$A, ">="&F$1, 'Transaction Ledger'!$A:$A, "<="&EOMONTH(F$1,0)))) | G8: =IF(G$1="2026 Total", SUM($B3:R3), IF(G$1="2027 Total", SUM($O3:AE3), SUMIFS('Transaction Ledger'!$G:$G, 'Transaction Ledger'!$H:$H, "Compute/API Expense", 'Transaction Ledger'!$A:$A, ">="&G$1, 'Transaction Ledger'!$A:$A, "<="&EOMONTH(G$1,0)))) | H8: =IF(H$1="2026 Total", SUM($B3:S3), IF(H$1="2027 Total", SUM($O3:AF3), SUMIFS('Transaction Ledger'!$G:$G, 'Transaction Ledger'!$H:$H, "Compute/API Expense", 'Transaction Ledger'!$A:$A, ">="&H$1, 'Transaction Ledger'!$A:$A, "<="&EOMONTH(H$1,0)))) | I8: 0 | J8: =IF(J$1="2026 Total", SUM($B3:U3), IF(J$1="2027 Total", SUM($O3:AH3), SUMIFS('Transaction Ledger'!$G:$G, 'Transaction Ledger'!$H:$H, "Compute/API Expense", 'Transaction Ledger'!$A:$A, ">="&J$1, 'Transaction Ledger'!$A:$A, "<="&EOMONTH(J$1,0)))) | K8: =IF(K$1="2026 Total", SUM($B3:V3), IF(K$1="2027 Total", SUM($O3:AI3), SUMIFS('Transaction Ledger'!$G:$G, 'Transaction Ledger'!$H:$H, "Compute/API Expense", 'Transaction Ledger'!$A:$A, ">="&K$1, 'Transaction Ledger'!$A:$A, "<="&EOMONTH(K$1,0)))) | L8: =IF(L$1="2026 Total", SUM($B3:W3), IF(L$1="2027 Total", SUM($O3:AJ3), SUMIFS('Transaction Ledger'!$G:$G, 'Transaction Ledger'!$H:$H, "Compute/API Expense", 'Transaction Ledger'!$A:$A, ">="&L$1, 'Transaction Ledger'!$A:$A, "<="&EOMONTH(L$1,0)))) | M8: =IF(M$1="2026 Total", SUM($B3:X3), IF(M$1="2027 Total", SUM($O3:AK3), SUMIFS('Transaction Ledger'!$G:$G, 'Transaction Ledger'!$H:$H, "Compute/API Expense", 'Transaction Ledger'!$A:$A, ">="&M$1, 'Transaction Ledger'!$A:$A, "<="&EOMONTH(M$1,0)))) | N8: =SUM(B8:M8) | O8: =IF(O$1="2026 Total", SUM($B3:Z3), IF(O$1="2027 Total", SUM($O3:AM3), SUMIFS('Transaction Ledger'!$G:$G, 'Transaction Ledger'!$H:$H, "Compute/API Expense", 'Transaction Ledger'!$A:$A, ">="&O$1, 'Transaction Ledger'!$A:$A, "<="&EOMONTH(O$1,0)))) | P8: =IF(P$1="2026 Total", SUM($B3:AA3), IF(P$1="2027 Total", SUM($O3:AN3), SUMIFS('Transaction Ledger'!$G:$G, 'Transaction Ledger'!$H:$H, "Compute/API Expense", 'Transaction Ledger'!$A:$A, ">="&P$1, 'Transaction Ledger'!$A:$A, "<="&EOMONTH(P$1,0)))) | Q8: =IF(Q$1="2026 Total", SUM($B3:AB3), IF(Q$1="2027 Total", SUM($O3:AO3), SUMIFS('Transaction Ledger'!$G:$G, 'Transaction Ledger'!$H:$H, "Compute/API Expense", 'Transaction Ledger'!$A:$A, ">="&Q$1, 'Transaction Ledger'!$A:$A, "<="&EOMONTH(Q$1,0)))) | R8: =IF(R$1="2026 Total", SUM($B3:AC3), IF(R$1="2027 Total", SUM($O3:AP3), SUMIFS('Transaction Ledger'!$G:$G, 'Transaction Ledger'!$H:$H, "Compute/API Expense", 'Transaction Ledger'!$A:$A, ">="&R$1, 'Transaction Ledger'!$A:$A, "<="&EOMONTH(R$1,0)))) | S8: =IF(S$1="2026 Total", SUM($B3:AD3), IF(S$1="2027 Total", SUM($O3:AQ3), SUMIFS('Transaction Ledger'!$G:$G, 'Transaction Ledger'!$H:$H, "Compute/API Expense", 'Transaction Ledger'!$A:$A, ">="&S$1, 'Transaction Ledger'!$A:$A, "<="&EOMONTH(S$1,0)))) | T8: =IF(T$1="2026 Total", SUM($B3:AE3), IF(T$1="2027 Total", SUM($O3:AR3), SUMIFS('Transaction Ledger'!$G:$G, 'Transaction Ledger'!$H:$H, "Compute/API Expense", 'Transaction Ledger'!$A:$A, ">="&T$1, 'Transaction Ledger'!$A:$A, "<="&EOMONTH(T$1,0)))) | U8: =IF(U$1="2026 Total", SUM($B3:AF3), IF(U$1="2027 Total", SUM($O3:AS3), SUMIFS('Transaction Ledger'!$G:$G, 'Transaction Ledger'!$H:$H, "Compute/API Expense", 'Transaction Ledger'!$A:$A, ">="&U$1, 'Transaction Ledger'!$A:$A, "<="&EOMONTH(U$1,0)))) | V8: =IF(V$1="2026 Total", SUM($B3:AG3), IF(V$1="2027 Total", SUM($O3:AT3), SUMIFS('Transaction Ledger'!$G:$G, 'Transaction Ledger'!$H:$H, "Compute/API Expense", 'Transaction Ledger'!$A:$A, ">="&V$1, 'Transaction Ledger'!$A:$A, "<="&EOMONTH(V$1,0)))) | ... Z8: =IF(Z$1="2026 Total", SUM($B3:AK3), IF(Z$1="2027 Total", SUM($O3:AX3), SUMIFS('Transaction Ledger'!$G:$G, 'Transaction Ledger'!$H:$H, "Compute/API Expense", 'Transaction Ledger'!$A:$A, ">="&Z$1, 'Transaction Ledger'!$A:$A, "<="&EOMONTH(Z$1,0)))) | AA8: =SUM(O8:Z8)
A9: API Tokens | B9: =IF(B$1="2026 Total", SUM($B3:M3), IF(B$1="2027 Total", SUM($O3:Z3), SUMIFS('Transaction Ledger'!$G:$G, 'Transaction Ledger'!$H:$H, "API Tokens", 'Transaction Ledger'!$A:$A, ">="&B$1, 'Transaction Ledger'!$A:$A, "<="&EOMONTH(B$1,0)))) | C9: =IF(C$1="2026 Total", SUM($B3:N3), IF(C$1="2027 Total", SUM($O3:AA3), SUMIFS('Transaction Ledger'!$G:$G, 'Transaction Ledger'!$H:$H, "API Tokens", 'Transaction Ledger'!$A:$A, ">="&C$1, 'Transaction Ledger'!$A:$A, "<="&EOMONTH(C$1,0)))) | D9: =IF(D$1="2026 Total", SUM($B3:O3), IF(D$1="2027 Total", SUM($O3:AB3), SUMIFS('Transaction Ledger'!$G:$G, 'Transaction Ledger'!$H:$H, "API Tokens", 'Transaction Ledger'!$A:$A, ">="&D$1, 'Transaction Ledger'!$A:$A, "<="&EOMONTH(D$1,0)))) | E9: =IF(E$1="2026 Total", SUM($B3:P3), IF(E$1="2027 Total", SUM($O3:AC3), SUMIFS('Transaction Ledger'!$G:$G, 'Transaction Ledger'!$H:$H, "API Tokens", 'Transaction Ledger'!$A:$A, ">="&E$1, 'Transaction Ledger'!$A:$A, "<="&EOMONTH(E$1,0)))) | F9: =IF(F$1="2026 Total", SUM($B3:Q3), IF(F$1="2027 Total", SUM($O3:AD3), SUMIFS('Transaction Ledger'!$G:$G, 'Transaction Ledger'!$H:$H, "API Tokens", 'Transaction Ledger'!$A:$A, ">="&F$1, 'Transaction Ledger'!$A:$A, "<="&EOMONTH(F$1,0)))) | G9: =IF(G$1="2026 Total", SUM($B3:R3), IF(G$1="2027 Total", SUM($O3:AE3), SUMIFS('Transaction Ledger'!$G:$G, 'Transaction Ledger'!$H:$H, "API Tokens", 'Transaction Ledger'!$A:$A, ">="&G$1, 'Transaction Ledger'!$A:$A, "<="&EOMONTH(G$1,0)))) | H9: =IF(H$1="2026 Total", SUM($B3:S3), IF(H$1="2027 Total", SUM($O3:AF3), SUMIFS('Transaction Ledger'!$G:$G, 'Transaction Ledger'!$H:$H, "API Tokens", 'Transaction Ledger'!$A:$A, ">="&H$1, 'Transaction Ledger'!$A:$A, "<="&EOMONTH(H$1,0)))) | I9: 0 | J9: =IF(J$1="2026 Total", SUM($B3:U3), IF(J$1="2027 Total", SUM($O3:AH3), SUMIFS('Transaction Ledger'!$G:$G, 'Transaction Ledger'!$H:$H, "API Tokens", 'Transaction Ledger'!$A:$A, ">="&J$1, 'Transaction Ledger'!$A:$A, "<="&EOMONTH(J$1,0)))) | K9: =IF(K$1="2026 Total", SUM($B3:V3), IF(K$1="2027 Total", SUM($O3:AI3), SUMIFS('Transaction Ledger'!$G:$G, 'Transaction Ledger'!$H:$H, "API Tokens", 'Transaction Ledger'!$A:$A, ">="&K$1, 'Transaction Ledger'!$A:$A, "<="&EOMONTH(K$1,0)))) | L9: =IF(L$1="2026 Total", SUM($B3:W3), IF(L$1="2027 Total", SUM($O3:AJ3), SUMIFS('Transaction Ledger'!$G:$G, 'Transaction Ledger'!$H:$H, "API Tokens", 'Transaction Ledger'!$A:$A, ">="&L$1, 'Transaction Ledger'!$A:$A, "<="&EOMONTH(L$1,0)))) | M9: =IF(M$1="2026 Total", SUM($B3:X3), IF(M$1="2027 Total", SUM($O3:AK3), SUMIFS('Transaction Ledger'!$G:$G, 'Transaction Ledger'!$H:$H, "API Tokens", 'Transaction Ledger'!$A:$A, ">="&M$1, 'Transaction Ledger'!$A:$A, "<="&EOMONTH(M$1,0)))) | N9: =SUM(B9:M9) | O9: =IF(O$1="2026 Total", SUM($B3:Z3), IF(O$1="2027 Total", SUM($O3:AM3), SUMIFS('Transaction Ledger'!$G:$G, 'Transaction Ledger'!$H:$H, "API Tokens", 'Transaction Ledger'!$A:$A, ">="&O$1, 'Transaction Ledger'!$A:$A, "<="&EOMONTH(O$1,0)))) | P9: =IF(P$1="2026 Total", SUM($B3:AA3), IF(P$1="2027 Total", SUM($O3:AN3), SUMIFS('Transaction Ledger'!$G:$G, 'Transaction Ledger'!$H:$H, "API Tokens", 'Transaction Ledger'!$A:$A, ">="&P$1, 'Transaction Ledger'!$A:$A, "<="&EOMONTH(P$1,0)))) | Q9: =IF(Q$1="2026 Total", SUM($B3:AB3), IF(Q$1="2027 Total", SUM($O3:AO3), SUMIFS('Transaction Ledger'!$G:$G, 'Transaction Ledger'!$H:$H, "API Tokens", 'Transaction Ledger'!$A:$A, ">="&Q$1, 'Transaction Ledger'!$A:$A, "<="&EOMONTH(Q$1,0)))) | R9: =IF(R$1="2026 Total", SUM($B3:AC3), IF(R$1="2027 Total", SUM($O3:AP3), SUMIFS('Transaction Ledger'!$G:$G, 'Transaction Ledger'!$H:$H, "API Tokens", 'Transaction Ledger'!$A:$A, ">="&R$1, 'Transaction Ledger'!$A:$A, "<="&EOMONTH(R$1,0)))) | S9: =IF(S$1="2026 Total", SUM($B3:AD3), IF(S$1="2027 Total", SUM($O3:AQ3), SUMIFS('Transaction Ledger'!$G:$G, 'Transaction Ledger'!$H:$H, "API Tokens", 'Transaction Ledger'!$A:$A, ">="&S$1, 'Transaction Ledger'!$A:$A, "<="&EOMONTH(S$1,0)))) | T9: =IF(T$1="2026 Total", SUM($B3:AE3), IF(T$1="2027 Total", SUM($O3:AR3), SUMIFS('Transaction Ledger'!$G:$G, 'Transaction Ledger'!$H:$H, "API Tokens", 'Transaction Ledger'!$A:$A, ">="&T$1, 'Transaction Ledger'!$A:$A, "<="&EOMONTH(T$1,0)))) | U9: =IF(U$1="2026 Total", SUM($B3:AF3), IF(U$1="2027 Total", SUM($O3:AS3), SUMIFS('Transaction Ledger'!$G:$G, 'Transaction Ledger'!$H:$H, "API Tokens", 'Transaction Ledger'!$A:$A, ">="&U$1, 'Transaction Ledger'!$A:$A, "<="&EOMONTH(U$1,0)))) | V9: =IF(V$1="2026 Total", SUM($B3:AG3), IF(V$1="2027 Total", SUM($O3:AT3), SUMIFS('Transaction Ledger'!$G:$G, 'Transaction Ledger'!$H:$H, "API Tokens", 'Transaction Ledger'!$A:$A, ">="&V$1, 'Transaction Ledger'!$A:$A, "<="&EOMONTH(V$1,0)))) | ... Z9: =IF(Z$1="2026 Total", SUM($B3:AK3), IF(Z$1="2027 Total", SUM($O3:AX3), SUMIFS('Transaction Ledger'!$G:$G, 'Transaction Ledger'!$H:$H, "API Tokens", 'Transaction Ledger'!$A:$A, ">="&Z$1, 'Transaction Ledger'!$A:$A, "<="&EOMONTH(Z$1,0)))) | AA9: =SUM(O9:Z9)
A10: Total COGS | B10: =SUM(B8:B9) | C10: =SUM(C8:C9) | D10: =SUM(D8:D9) | E10: =SUM(E8:E9) | F10: =SUM(F8:F9) | G10: =SUM(G8:G9) | H10: =SUM(H8:H9) | I10: =SUM(I8:I9) | ... M10: =SUM(M8:M9) | N10: =SUM(B10:M10) | O10: =SUM(O8:O9) | P10: =SUM(P8:P9) | Q10: =SUM(Q8:Q9) | R10: =SUM(R8:R9) | S10: =SUM(S8:S9) | T10: =SUM(T8:T9) | U10: =SUM(U8:U9) | V10: =SUM(V8:V9) | ... Z10: =SUM(Z8:Z9) | AA10: =SUM(O10:Z10)
A11: Gross Profit | B11: =B6-B10 | C11: =C6-C10 | D11: =D6-D10 | E11: =E6-E10 | F11: =F6-F10 | G11: =G6-G10 | H11: =H6-H10 | I11: 27205 | J11: 22000 | K11: 31000 | L11: 40000 | M11: 48000 | N11: 151605 | O11: 57000 | P11: 67000 | Q11: 77000 | R11: 86000 | S11: 93000 | T11: 100000 | U11: 100000 | V11: 100000 | W11: 100000 | X11: 100000 | Y11: 100000 | Z11: 100000 | AA11: 1080000
A12: Operating Expenses
A13: Software Tools | B13: =IF(B$1="2026 Total", SUM($B3:M3), IF(B$1="2027 Total", SUM($O3:Z3), SUMIFS('Transaction Ledger'!$G:$G, 'Transaction Ledger'!$H:$H, "Software Subscription", 'Transaction Ledger'!$A:$A, ">="&B$1, 'Transaction Ledger'!$A:$A, "<="&EOMONTH(B$1,0)))) | C13: =IF(C$1="2026 Total", SUM($B3:N3), IF(C$1="2027 Total", SUM($O3:AA3), SUMIFS('Transaction Ledger'!$G:$G, 'Transaction Ledger'!$H:$H, "Software Subscription", 'Transaction Ledger'!$A:$A, ">="&C$1, 'Transaction Ledger'!$A:$A, "<="&EOMONTH(C$1,0)))) | D13: =IF(D$1="2026 Total", SUM($B3:O3), IF(D$1="2027 Total", SUM($O3:AB3), SUMIFS('Transaction Ledger'!$G:$G, 'Transaction Ledger'!$H:$H, "Software Subscription", 'Transaction Ledger'!$A:$A, ">="&D$1, 'Transaction Ledger'!$A:$A, "<="&EOMONTH(D$1,0)))) | E13: =IF(E$1="2026 Total", SUM($B3:P3), IF(E$1="2027 Total", SUM($O3:AC3), SUMIFS('Transaction Ledger'!$G:$G, 'Transaction Ledger'!$H:$H, "Software Subscription", 'Transaction Ledger'!$A:$A, ">="&E$1, 'Transaction Ledger'!$A:$A, "<="&EOMONTH(E$1,0)))) | F13: =IF(F$1="2026 Total", SUM($B3:Q3), IF(F$1="2027 Total", SUM($O3:AD3), SUMIFS('Transaction Ledger'!$G:$G, 'Transaction Ledger'!$H:$H, "Software Subscription", 'Transaction Ledger'!$A:$A, ">="&F$1, 'Transaction Ledger'!$A:$A, "<="&EOMONTH(F$1,0)))) | G13: =IF(G$1="2026 Total", SUM($B3:R3), IF(G$1="2027 Total", SUM($O3:AE3), SUMIFS('Transaction Ledger'!$G:$G, 'Transaction Ledger'!$H:$H, "Software Subscription", 'Transaction Ledger'!$A:$A, ">="&G$1, 'Transaction Ledger'!$A:$A, "<="&EOMONTH(G$1,0)))) | H13: =IF(H$1="2026 Total", SUM($B3:S3), IF(H$1="2027 Total", SUM($O3:AF3), SUMIFS('Transaction Ledger'!$G:$G, 'Transaction Ledger'!$H:$H, "Software Subscription", 'Transaction Ledger'!$A:$A, ">="&H$1, 'Transaction Ledger'!$A:$A, "<="&EOMONTH(H$1,0)))) | I13: 0 | J13: =IF(J$1="2026 Total", SUM($B3:U3), IF(J$1="2027 Total", SUM($O3:AH3), SUMIFS('Transaction Ledger'!$G:$G, 'Transaction Ledger'!$H:$H, "Software Subscription", 'Transaction Ledger'!$A:$A, ">="&J$1, 'Transaction Ledger'!$A:$A, "<="&EOMONTH(J$1,0)))) | K13: =IF(K$1="2026 Total", SUM($B3:V3), IF(K$1="2027 Total", SUM($O3:AI3), SUMIFS('Transaction Ledger'!$G:$G, 'Transaction Ledger'!$H:$H, "Software Subscription", 'Transaction Ledger'!$A:$A, ">="&K$1, 'Transaction Ledger'!$A:$A, "<="&EOMONTH(K$1,0)))) | L13: =IF(L$1="2026 Total", SUM($B3:W3), IF(L$1="2027 Total", SUM($O3:AJ3), SUMIFS('Transaction Ledger'!$G:$G, 'Transaction Ledger'!$H:$H, "Software Subscription", 'Transaction Ledger'!$A:$A, ">="&L$1, 'Transaction Ledger'!$A:$A, "<="&EOMONTH(L$1,0)))) | M13: =IF(M$1="2026 Total", SUM($B3:X3), IF(M$1="2027 Total", SUM($O3:AK3), SUMIFS('Transaction Ledger'!$G:$G, 'Transaction Ledger'!$H:$H, "Software Subscription", 'Transaction Ledger'!$A:$A, ">="&M$1, 'Transaction Ledger'!$A:$A, "<="&EOMONTH(M$1,0)))) | N13: =SUM(B13:M13) | O13: =IF(O$1="2026 Total", SUM($B3:Z3), IF(O$1="2027 Total", SUM($O3:AM3), SUMIFS('Transaction Ledger'!$G:$G, 'Transaction Ledger'!$H:$H, "Software Subscription", 'Transaction Ledger'!$A:$A, ">="&O$1, 'Transaction Ledger'!$A:$A, "<="&EOMONTH(O$1,0)))) | P13: =IF(P$1="2026 Total", SUM($B3:AA3), IF(P$1="2027 Total", SUM($O3:AN3), SUMIFS('Transaction Ledger'!$G:$G, 'Transaction Ledger'!$H:$H, "Software Subscription", 'Transaction Ledger'!$A:$A, ">="&P$1, 'Transaction Ledger'!$A:$A, "<="&EOMONTH(P$1,0)))) | Q13: =IF(Q$1="2026 Total", SUM($B3:AB3), IF(Q$1="2027 Total", SUM($O3:AO3), SUMIFS('Transaction Ledger'!$G:$G, 'Transaction Ledger'!$H:$H, "Software Subscription", 'Transaction Ledger'!$A:$A, ">="&Q$1, 'Transaction Ledger'!$A:$A, "<="&EOMONTH(Q$1,0)))) | R13: =IF(R$1="2026 Total", SUM($B3:AC3), IF(R$1="2027 Total", SUM($O3:AP3), SUMIFS('Transaction Ledger'!$G:$G, 'Transaction Ledger'!$H:$H, "Software Subscription", 'Transaction Ledger'!$A:$A, ">="&R$1, 'Transaction Ledger'!$A:$A, "<="&EOMONTH(R$1,0)))) | S13: =IF(S$1="2026 Total", SUM($B3:AD3), IF(S$1="2027 Total", SUM($O3:AQ3), SUMIFS('Transaction Ledger'!$G:$G, 'Transaction Ledger'!$H:$H, "Software Subscription", 'Transaction Ledger'!$A:$A, ">="&S$1, 'Transaction Ledger'!$A:$A, "<="&EOMONTH(S$1,0)))) | T13: =IF(T$1="2026 Total", SUM($B3:AE3), IF(T$1="2027 Total", SUM($O3:AR3), SUMIFS('Transaction Ledger'!$G:$G, 'Transaction Ledger'!$H:$H, "Software Subscription", 'Transaction Ledger'!$A:$A, ">="&T$1, 'Transaction Ledger'!$A:$A, "<="&EOMONTH(T$1,0)))) | U13: =IF(U$1="2026 Total", SUM($B3:AF3), IF(U$1="2027 Total", SUM($O3:AS3), SUMIFS('Transaction Ledger'!$G:$G, 'Transaction Ledger'!$H:$H, "Software Subscription", 'Transaction Ledger'!$A:$A, ">="&U$1, 'Transaction Ledger'!$A:$A, "<="&EOMONTH(U$1,0)))) | V13: =IF(V$1="2026 Total", SUM($B3:AG3), IF(V$1="2027 Total", SUM($O3:AT3), SUMIFS('Transaction Ledger'!$G:$G, 'Transaction Ledger'!$H:$H, "Software Subscription", 'Transaction Ledger'!$A:$A, ">="&V$1, 'Transaction Ledger'!$A:$A, "<="&EOMONTH(V$1,0)))) | ... Z13: =IF(Z$1="2026 Total", SUM($B3:AK3), IF(Z$1="2027 Total", SUM($O3:AX3), SUMIFS('Transaction Ledger'!$G:$G, 'Transaction Ledger'!$H:$H, "Software Subscription", 'Transaction Ledger'!$A:$A, ">="&Z$1, 'Transaction Ledger'!$A:$A, "<="&EOMONTH(Z$1,0)))) | AA13: =SUM(O13:Z13)
A14: Legal/Admin | B14: =IF(B$1="2026 Total", SUM($B3:M3), IF(B$1="2027 Total", SUM($O3:Z3), SUMIFS('Transaction Ledger'!$G:$G, 'Transaction Ledger'!$H:$H, "Legal/Admin", 'Transaction Ledger'!$A:$A, ">="&B$1, 'Transaction Ledger'!$A:$A, "<="&EOMONTH(B$1,0)))) | C14: =IF(C$1="2026 Total", SUM($B3:N3), IF(C$1="2027 Total", SUM($O3:AA3), SUMIFS('Transaction Ledger'!$G:$G, 'Transaction Ledger'!$H:$H, "Legal/Admin", 'Transaction Ledger'!$A:$A, ">="&C$1, 'Transaction Ledger'!$A:$A, "<="&EOMONTH(C$1,0)))) | D14: =IF(D$1="2026 Total", SUM($B3:O3), IF(D$1="2027 Total", SUM($O3:AB3), SUMIFS('Transaction Ledger'!$G:$G, 'Transaction Ledger'!$H:$H, "Legal/Admin", 'Transaction Ledger'!$A:$A, ">="&D$1, 'Transaction Ledger'!$A:$A, "<="&EOMONTH(D$1,0)))) | E14: =IF(E$1="2026 Total", SUM($B3:P3), IF(E$1="2027 Total", SUM($O3:AC3), SUMIFS('Transaction Ledger'!$G:$G, 'Transaction Ledger'!$H:$H, "Legal/Admin", 'Transaction Ledger'!$A:$A, ">="&E$1, 'Transaction Ledger'!$A:$A, "<="&EOMONTH(E$1,0)))) | F14: =IF(F$1="2026 Total", SUM($B3:Q3), IF(F$1="2027 Total", SUM($O3:AD3), SUMIFS('Transaction Ledger'!$G:$G, 'Transaction Ledger'!$H:$H, "Legal/Admin", 'Transaction Ledger'!$A:$A, ">="&F$1, 'Transaction Ledger'!$A:$A, "<="&EOMONTH(F$1,0)))) | G14: =IF(G$1="2026 Total", SUM($B3:R3), IF(G$1="2027 Total", SUM($O3:AE3), SUMIFS('Transaction Ledger'!$G:$G, 'Transaction Ledger'!$H:$H, "Legal/Admin", 'Transaction Ledger'!$A:$A, ">="&G$1, 'Transaction Ledger'!$A:$A, "<="&EOMONTH(G$1,0)))) | H14: =IF(H$1="2026 Total", SUM($B3:S3), IF(H$1="2027 Total", SUM($O3:AF3), SUMIFS('Transaction Ledger'!$G:$G, 'Transaction Ledger'!$H:$H, "Legal/Admin", 'Transaction Ledger'!$A:$A, ">="&H$1, 'Transaction Ledger'!$A:$A, "<="&EOMONTH(H$1,0)))) | I14: 0 | J14: =IF(J$1="2026 Total", SUM($B3:U3), IF(J$1="2027 Total", SUM($O3:AH3), SUMIFS('Transaction Ledger'!$G:$G, 'Transaction Ledger'!$H:$H, "Legal/Admin", 'Transaction Ledger'!$A:$A, ">="&J$1, 'Transaction Ledger'!$A:$A, "<="&EOMONTH(J$1,0)))) | K14: =IF(K$1="2026 Total", SUM($B3:V3), IF(K$1="2027 Total", SUM($O3:AI3), SUMIFS('Transaction Ledger'!$G:$G, 'Transaction Ledger'!$H:$H, "Legal/Admin", 'Transaction Ledger'!$A:$A, ">="&K$1, 'Transaction Ledger'!$A:$A, "<="&EOMONTH(K$1,0)))) | L14: =IF(L$1="2026 Total", SUM($B3:W3), IF(L$1="2027 Total", SUM($O3:AJ3), SUMIFS('Transaction Ledger'!$G:$G, 'Transaction Ledger'!$H:$H, "Legal/Admin", 'Transaction Ledger'!$A:$A, ">="&L$1, 'Transaction Ledger'!$A:$A, "<="&EOMONTH(L$1,0)))) | M14: =IF(M$1="2026 Total", SUM($B3:X3), IF(M$1="2027 Total", SUM($O3:AK3), SUMIFS('Transaction Ledger'!$G:$G, 'Transaction Ledger'!$H:$H, "Legal/Admin", 'Transaction Ledger'!$A:$A, ">="&M$1, 'Transaction Ledger'!$A:$A, "<="&EOMONTH(M$1,0)))) | N14: =SUM(B14:M14) | O14: =IF(O$1="2026 Total", SUM($B3:Z3), IF(O$1="2027 Total", SUM($O3:AM3), SUMIFS('Transaction Ledger'!$G:$G, 'Transaction Ledger'!$H:$H, "Legal/Admin", 'Transaction Ledger'!$A:$A, ">="&O$1, 'Transaction Ledger'!$A:$A, "<="&EOMONTH(O$1,0)))) | P14: =IF(P$1="2026 Total", SUM($B3:AA3), IF(P$1="2027 Total", SUM($O3:AN3), SUMIFS('Transaction Ledger'!$G:$G, 'Transaction Ledger'!$H:$H, "Legal/Admin", 'Transaction Ledger'!$A:$A, ">="&P$1, 'Transaction Ledger'!$A:$A, "<="&EOMONTH(P$1,0)))) | Q14: =IF(Q$1="2026 Total", SUM($B3:AB3), IF(Q$1="2027 Total", SUM($O3:AO3), SUMIFS('Transaction Ledger'!$G:$G, 'Transaction Ledger'!$H:$H, "Legal/Admin", 'Transaction Ledger'!$A:$A, ">="&Q$1, 'Transaction Ledger'!$A:$A, "<="&EOMONTH(Q$1,0)))) | R14: =IF(R$1="2026 Total", SUM($B3:AC3), IF(R$1="2027 Total", SUM($O3:AP3), SUMIFS('Transaction Ledger'!$G:$G, 'Transaction Ledger'!$H:$H, "Legal/Admin", 'Transaction Ledger'!$A:$A, ">="&R$1, 'Transaction Ledger'!$A:$A, "<="&EOMONTH(R$1,0)))) | S14: =IF(S$1="2026 Total", SUM($B3:AD3), IF(S$1="2027 Total", SUM($O3:AQ3), SUMIFS('Transaction Ledger'!$G:$G, 'Transaction Ledger'!$H:$H, "Legal/Admin", 'Transaction Ledger'!$A:$A, ">="&S$1, 'Transaction Ledger'!$A:$A, "<="&EOMONTH(S$1,0)))) | T14: =IF(T$1="2026 Total", SUM($B3:AE3), IF(T$1="2027 Total", SUM($O3:AR3), SUMIFS('Transaction Ledger'!$G:$G, 'Transaction Ledger'!$H:$H, "Legal/Admin", 'Transaction Ledger'!$A:$A, ">="&T$1, 'Transaction Ledger'!$A:$A, "<="&EOMONTH(T$1,0)))) | U14: =IF(U$1="2026 Total", SUM($B3:AF3), IF(U$1="2027 Total", SUM($O3:AS3), SUMIFS('Transaction Ledger'!$G:$G, 'Transaction Ledger'!$H:$H, "Legal/Admin", 'Transaction Ledger'!$A:$A, ">="&U$1, 'Transaction Ledger'!$A:$A, "<="&EOMONTH(U$1,0)))) | V14: =IF(V$1="2026 Total", SUM($B3:AG3), IF(V$1="2027 Total", SUM($O3:AT3), SUMIFS('Transaction Ledger'!$G:$G, 'Transaction Ledger'!$H:$H, "Legal/Admin", 'Transaction Ledger'!$A:$A, ">="&V$1, 'Transaction Ledger'!$A:$A, "<="&EOMONTH(V$1,0)))) | ... Z14: =IF(Z$1="2026 Total", SUM($B3:AK3), IF(Z$1="2027 Total", SUM($O3:AX3), SUMIFS('Transaction Ledger'!$G:$G, 'Transaction Ledger'!$H:$H, "Legal/Admin", 'Transaction Ledger'!$A:$A, ">="&Z$1, 'Transaction Ledger'!$A:$A, "<="&EOMONTH(Z$1,0)))) | AA14: =SUM(O14:Z14)
A15: Marketing | B15: =IF(B$1="2026 Total", SUM($B3:M3), IF(B$1="2027 Total", SUM($O3:Z3), SUMIFS('Transaction Ledger'!$G:$G, 'Transaction Ledger'!$H:$H, "Marketing", 'Transaction Ledger'!$A:$A, ">="&B$1, 'Transaction Ledger'!$A:$A, "<="&EOMONTH(B$1,0)))) | C15: =IF(C$1="2026 Total", SUM($B3:N3), IF(C$1="2027 Total", SUM($O3:AA3), SUMIFS('Transaction Ledger'!$G:$G, 'Transaction Ledger'!$H:$H, "Marketing", 'Transaction Ledger'!$A:$A, ">="&C$1, 'Transaction Ledger'!$A:$A, "<="&EOMONTH(C$1,0)))) | D15: =IF(D$1="2026 Total", SUM($B3:O3), IF(D$1="2027 Total", SUM($O3:AB3), SUMIFS('Transaction Ledger'!$G:$G, 'Transaction Ledger'!$H:$H, "Marketing", 'Transaction Ledger'!$A:$A, ">="&D$1, 'Transaction Ledger'!$A:$A, "<="&EOMONTH(D$1,0)))) | E15: =IF(E$1="2026 Total", SUM($B3:P3), IF(E$1="2027 Total", SUM($O3:AC3), SUMIFS('Transaction Ledger'!$G:$G, 'Transaction Ledger'!$H:$H, "Marketing", 'Transaction Ledger'!$A:$A, ">="&E$1, 'Transaction Ledger'!$A:$A, "<="&EOMONTH(E$1,0)))) | F15: =IF(F$1="2026 Total", SUM($B3:Q3), IF(F$1="2027 Total", SUM($O3:AD3), SUMIFS('Transaction Ledger'!$G:$G, 'Transaction Ledger'!$H:$H, "Marketing", 'Transaction Ledger'!$A:$A, ">="&F$1, 'Transaction Ledger'!$A:$A, "<="&EOMONTH(F$1,0)))) | G15: =IF(G$1="2026 Total", SUM($B3:R3), IF(G$1="2027 Total", SUM($O3:AE3), SUMIFS('Transaction Ledger'!$G:$G, 'Transaction Ledger'!$H:$H, "Marketing", 'Transaction Ledger'!$A:$A, ">="&G$1, 'Transaction Ledger'!$A:$A, "<="&EOMONTH(G$1,0)))) | H15: =IF(H$1="2026 Total", SUM($B3:S3), IF(H$1="2027 Total", SUM($O3:AF3), SUMIFS('Transaction Ledger'!$G:$G, 'Transaction Ledger'!$H:$H, "Marketing", 'Transaction Ledger'!$A:$A, ">="&H$1, 'Transaction Ledger'!$A:$A, "<="&EOMONTH(H$1,0)))) | I15: 0 | J15: =IF(J$1="2026 Total", SUM($B3:U3), IF(J$1="2027 Total", SUM($O3:AH3), SUMIFS('Transaction Ledger'!$G:$G, 'Transaction Ledger'!$H:$H, "Marketing", 'Transaction Ledger'!$A:$A, ">="&J$1, 'Transaction Ledger'!$A:$A, "<="&EOMONTH(J$1,0)))) | K15: =IF(K$1="2026 Total", SUM($B3:V3), IF(K$1="2027 Total", SUM($O3:AI3), SUMIFS('Transaction Ledger'!$G:$G, 'Transaction Ledger'!$H:$H, "Marketing", 'Transaction Ledger'!$A:$A, ">="&K$1, 'Transaction Ledger'!$A:$A, "<="&EOMONTH(K$1,0)))) | L15: =IF(L$1="2026 Total", SUM($B3:W3), IF(L$1="2027 Total", SUM($O3:AJ3), SUMIFS('Transaction Ledger'!$G:$G, 'Transaction Ledger'!$H:$H, "Marketing", 'Transaction Ledger'!$A:$A, ">="&L$1, 'Transaction Ledger'!$A:$A, "<="&EOMONTH(L$1,0)))) | M15: =IF(M$1="2026 Total", SUM($B3:X3), IF(M$1="2027 Total", SUM($O3:AK3), SUMIFS('Transaction Ledger'!$G:$G, 'Transaction Ledger'!$H:$H, "Marketing", 'Transaction Ledger'!$A:$A, ">="&M$1, 'Transaction Ledger'!$A:$A, "<="&EOMONTH(M$1,0)))) | N15: =SUM(B15:M15) | O15: =IF(O$1="2026 Total", SUM($B3:Z3), IF(O$1="2027 Total", SUM($O3:AM3), SUMIFS('Transaction Ledger'!$G:$G, 'Transaction Ledger'!$H:$H, "Marketing", 'Transaction Ledger'!$A:$A, ">="&O$1, 'Transaction Ledger'!$A:$A, "<="&EOMONTH(O$1,0)))) | P15: =IF(P$1="2026 Total", SUM($B3:AA3), IF(P$1="2027 Total", SUM($O3:AN3), SUMIFS('Transaction Ledger'!$G:$G, 'Transaction Ledger'!$H:$H, "Marketing", 'Transaction Ledger'!$A:$A, ">="&P$1, 'Transaction Ledger'!$A:$A, "<="&EOMONTH(P$1,0)))) | Q15: =IF(Q$1="2026 Total", SUM($B3:AB3), IF(Q$1="2027 Total", SUM($O3:AO3), SUMIFS('Transaction Ledger'!$G:$G, 'Transaction Ledger'!$H:$H, "Marketing", 'Transaction Ledger'!$A:$A, ">="&Q$1, 'Transaction Ledger'!$A:$A, "<="&EOMONTH(Q$1,0)))) | R15: =IF(R$1="2026 Total", SUM($B3:AC3), IF(R$1="2027 Total", SUM($O3:AP3), SUMIFS('Transaction Ledger'!$G:$G, 'Transaction Ledger'!$H:$H, "Marketing", 'Transaction Ledger'!$A:$A, ">="&R$1, 'Transaction Ledger'!$A:$A, "<="&EOMONTH(R$1,0)))) | S15: =IF(S$1="2026 Total", SUM($B3:AD3), IF(S$1="2027 Total", SUM($O3:AQ3), SUMIFS('Transaction Ledger'!$G:$G, 'Transaction Ledger'!$H:$H, "Marketing", 'Transaction Ledger'!$A:$A, ">="&S$1, 'Transaction Ledger'!$A:$A, "<="&EOMONTH(S$1,0)))) | T15: =IF(T$1="2026 Total", SUM($B3:AE3), IF(T$1="2027 Total", SUM($O3:AR3), SUMIFS('Transaction Ledger'!$G:$G, 'Transaction Ledger'!$H:$H, "Marketing", 'Transaction Ledger'!$A:$A, ">="&T$1, 'Transaction Ledger'!$A:$A, "<="&EOMONTH(T$1,0)))) | U15: =IF(U$1="2026 Total", SUM($B3:AF3), IF(U$1="2027 Total", SUM($O3:AS3), SUMIFS('Transaction Ledger'!$G:$G, 'Transaction Ledger'!$H:$H, "Marketing", 'Transaction Ledger'!$A:$A, ">="&U$1, 'Transaction Ledger'!$A:$A, "<="&EOMONTH(U$1,0)))) | V15: =IF(V$1="2026 Total", SUM($B3:AG3), IF(V$1="2027 Total", SUM($O3:AT3), SUMIFS('Transaction Ledger'!$G:$G, 'Transaction Ledger'!$H:$H, "Marketing", 'Transaction Ledger'!$A:$A, ">="&V$1, 'Transaction Ledger'!$A:$A, "<="&EOMONTH(V$1,0)))) | ... Z15: =IF(Z$1="2026 Total", SUM($B3:AK3), IF(Z$1="2027 Total", SUM($O3:AX3), SUMIFS('Transaction Ledger'!$G:$G, 'Transaction Ledger'!$H:$H, "Marketing", 'Transaction Ledger'!$A:$A, ">="&Z$1, 'Transaction Ledger'!$A:$A, "<="&EOMONTH(Z$1,0)))) | AA15: =SUM(O15:Z15)
A16: Total Operating Expenses | B16: =SUM(B13:B15) | C16: =SUM(C13:C15) | D16: =SUM(D13:D15) | E16: =SUM(E13:E15) | F16: =SUM(F13:F15) | G16: =SUM(G13:G15) | H16: =SUM(H13:H15) | I16: =SUM(I13:I15) | ... M16: =SUM(M13:M15) | N16: 10000 | O16: 4000 | P16: 4500 | Q16: 5000 | R16: 5000 | S16: 5500 | T16: 6000 | U16: 6000 | V16: 6000 | W16: 6000 | X16: 6000 | Y16: 6000 | Z16: 6000 | AA16: 60000
A17: EBITDA | B17: =B11-B16 | C17: =C11-C16 | D17: =D11-D16 | E17: =E11-E16 | F17: =F11-F16 | G17: =G11-G16 | H17: =H11-H16 | I17: 27205 | J17: 22000 | K17: 29000 | L17: 37500 | M17: 45000 | N17: 141605 | O17: 53000 | P17: 62500 | Q17: 72000 | R17: 81000 | S17: 87500 | T17: 94000 | U17: 94000 | V17: 94000 | W17: 94000 | X17: 94000 | Y17: 94000 | Z17: 94000 | AA17: 1020000
A18: Net Income | B18: =B17 | C18: =C17 | D18: =D17 | E18: =E17 | F18: =F17 | G18: =G17 | H18: =H17 | I18: 27205 | J18: 22000 | K18: 29000 | L18: 37500 | M18: 45000 | N18: 141605 | O18: 53000 | P18: 62500 | Q18: 72000 | R18: 81000 | S18: 87500 | T18: 94000 | U18: 94000 | V18: 94000 | W18: 94000 | X18: 94000 | Y18: 94000 | Z18: 94000 | AA18: 1020000

Sheet Balance Sheet
A1: Account | B1: Balance
A2: Assets
A3: Current Assets
A4: Cash & Cash Equivalents | B4: 5430
A5: Accounts Receivable | B5: 27175
A6: Total Assets | B6: 32605
A7: Liabilities | B7: 0
A8: Current Liabilities
A9: Accounts Payable | B9: 0
A10: Deferred Revenue | B10: 0
A11: Total Liabilities | B11: 0
A12: Owner's Equity
A13: Initial Contribution | B13: 0
A14: Retained Earnings | B14: 32605
A15: Balance Sheet Check | B15: =B6-B16
A16: Total Liabilities & Equity | B16: 32605
A17: Balance Check | B17: =B6-B16
B24: 30305

Sheet Cash Flow Statement
A1: Category | B1: Amount
A2: Cash Flow from Operating Activities
A3: Net Income | B3: 32605
A4: Adjustments for A/R changes | B4: -27175
A5: Net Cash from Operating Activities | B5: 5430
A6: Cash Flow from Investing Activities | B6: 0
A7: Cash Flow from Financing Activities | B7: ='Balance Sheet'!B13
A8: Net Change in Cash | B8: 5430
A9: Ending Cash Balance | B9: 5430
B10: 5430
B23: 5430
B25: 5430

Sheet Transaction Ledger
A1: Date | B1: Transaction ID | C1: Platform/Source | D1: Description | E1: Gross Amount | F1: Platform/Stripe Processing Fee | G1: Net Amount | H1: Category | I1: Status
A2: 46249 | B2: CB-001 | C2: Opire / Stripe | D2: claude-builders-bounty PR #3739 | E2: 50 | F2: 0 | G2: 50 | H2: Bounty Revenue | I2: Pending Merge
A3: 46249 | B3: CB-002 | C3: Opire / Stripe | D3: claude-builders-bounty PR #3740 | E3: 75 | F3: 0 | G3: 75 | H3: Bounty Revenue | I3: Pending Merge
A4: 46249 | B4: CB-003 | C4: Opire / Stripe | D4: claude-builders-bounty PR #3741 | E4: 100 | F4: 0 | G4: 100 | H4: Bounty Revenue | I4: Pending Merge
A5: 46250 | B5: AP-9914 | C5: Algora / Stripe | D5: PR #14841 | E5: 100 | F5: 0 | G5: 100 | H5: Bounty Revenue | I5: Closed (Unmerged)
A6: 46250 | B6: PD-924 | C6: Algora / Stripe | D6: PR #1016 | E6: 100 | F6: 0 | G6: 100 | H6: Bounty Revenue | I6: Closed (Unmerged)
A7: 46250 | B7: CB-004 | C7: Opire / Stripe | D7: claude-builders-bounty PR #3758 | E7: 150 | F7: 0 | G7: 150 | H7: Bounty Revenue | I7: Pending Merge
A8: 46251 | B8: CB-005 | C8: Opire / Stripe | D8: claude-builders-bounty PR #3760 | E8: 200 | F8: 0 | G8: 200 | H8: Bounty Revenue | I8: Pending Merge
A9: 46251 | B9: PD-2345 | C9: Algora / Stripe | D9: PR #2560 | E9: 75 | F9: 0 | G9: 75 | H9: Bounty Revenue | I9: Closed (Unmerged)
A10: 46252 | B10: PD-6532 | C10: Algora / Stripe | D10: ProjectDiscovery nuclei Issue #6532 (Typos CI Workflow Integration) | E10: 50 | F10: 0 | G10: 50 | H10: Bounty Revenue | I10: Closed (Unmerged)
A11: 46253 | B11: TSC-078 | C11: Algora / Stripe | D11: TSCircuit schematic-trace-solver Issue #78 (PR #837: Eliminate duplicate & extraneous trace lines) | E11: 100 | F11: 0 | G11: 100 | H11: Bounty Revenue | I11: Pending Merge
A12: 46254 | B12: PD-1828 | C12: Algora / Stripe | D12: ProjectDiscovery subfinder Issue #1828 (PR #1832: Fix crt.sh PgBouncer statement_timeout) | E12: 100 | F12: 0 | G12: 100 | H12: Bounty Revenue | I12: Merged / Settled
A13: 46254 | B13: PD-403 | C13: Algora / Stripe | D13: ProjectDiscovery dnsx Issue #403 (PR #1017: Add -query-type and -exclude-type flags) | E13: 100 | F13: 0 | G13: 100 | H13: Bounty Revenue | I13: Closed
... A149: 46266.829 | B149: TS-CIRCUIT-1033 | C149: Algora / Stripe | D149: tscircuit (PR #1033: two-pin terminal stub routing tests in schematic solver) | E149: 150 | F149: 0 | G149: 150 | H149: Bounty Revenue | I149: Pending Merge
A150: 46267.081 | B150: PD-KATANA-1798 | C150: Algora / Stripe | D150: ProjectDiscovery (PR #1798: dev-aligned robotstxt boundary tests in katana) | E150: ProjectDiscovery | F150: 200 | G150: 200 | H150: Bounty Revenue | I150: Pending Merge
A151: 46267.149 | B151: LILLY-SDK-399 | C151: Stellar / Algora | D151: Lilly-Protocol (PR #399: AgentClient 100% test coverage in lily-sdk) | E151: Lilly-Protocol | F151: 250 | G151: 250 | H151: Bounty Revenue | I151: Merged / Settled
A152: 46266.602 | B152: LILLY-FRONT-190 | C152: Stellar / Algora | D152: Lilly-Protocol (PR #190: shared SiteFooter component across section layouts) | E152: Lilly-Protocol | F152: 75 | G152: 75 | H152: Bounty Revenue | I152: Merged / Settled
A153: 46267.7 | B153: PERMIFY-3127 | C153: Algora / Stripe | D153: Permify (PR #3127: entity tuple validation regression tests) | E153: 250 | F153: 0 | G153: 250 | H153: Bounty Revenue | I153: Pending Merge
A154: 46267.701 | B154: CAP-SOFTWARE-2198 | C154: Algora / Stripe | D154: CapSoftware (PR #2198: WebRTC session description tests in Chrome extension) | E154: 200 | F154: 0 | G154: 200 | H154: Bounty Revenue | I154: Closed
A155: 46267.701 | B155: LILLY-STELLAR-278 | C155: Stellar / Algora | D155: Lilly-Protocol (PR #278: Soroban access controller authorization tests) | E155: 250 | F155: 0 | G155: 250 | H155: Bounty Revenue | I155: Pending Merge
A156: 46267.701 | B156: PD-KATANA-1799 | C156: Algora / Stripe | D156: ProjectDiscovery (PR #1799: robotstxt crawler boundary tests in katana) | E156: 200 | F156: 0 | G156: 200 | H156: Bounty Revenue | I156: Pending Merge
A157: 46267.701 | B157: TS-CIRCUIT-1041 | C157: Algora / Stripe | D157: tscircuit (PR #1041: two-pin terminal stub routing tests in schematic solver) | E157: 150 | F157: 0 | G157: 150 | H157: Bounty Revenue | I157: Pending Merge
A158: 46267.707 | B158: PERMIFY-3128 | C158: Algora / Stripe | D158: Permify (PR #3128: entity tuple validation regression tests) | E158: 250 | F158: 0 | G158: 250 | H158: Bounty Revenue | I158: Pending Merge
A159: 46267.707 | B159: CAP-SOFTWARE-2199 | C159: Algora / Stripe | D159: CapSoftware (PR #2199: WebRTC session description tests in Chrome extension) | E159: 200 | F159: 0 | G159: 200 | H159: Bounty Revenue | I159: Closed
A160: 46267.707 | B160: LILLY-STELLAR-279 | C160: Stellar / Algora | D160: Lilly-Protocol (PR #279: Soroban access controller authorization tests) | E160: 250 | F160: 0 | G160: 250 | H160: Bounty Revenue | I160: Pending Merge
A161: 46267.707 | B161: PD-KATANA-1800 | C161: Algora / Stripe | D161: ProjectDiscovery (PR #1800: robotstxt crawler boundary tests in katana) | E161: 200 | F161: 0 | G161: 200 | H161: Bounty Revenue | I161: Pending Merge
A162: 46267.707 | B162: TS-CIRCUIT-1042 | C162: Algora / Stripe | D162: tscircuit (PR #1042: two-pin terminal stub routing tests in schematic solver) | E162: 150 | F162: 0 | G162: 150 | H162: Bounty Revenue | I162: Pending Merge
A163: 46266 | B163: LILLY-186 | C163: Stellar / Algora | D163: Lilly-Protocol/lily-frontend (PR #186: docs(adr): add ADR 0001 for route-scaffold architecture (#47)) | E163: lily-frontend | F163: 75 | G163: 75 | H163: Bounty Revenue | I163: Merged / Settled
A164: 46266 | B164: LILLY-187 | C164: Stellar / Algora | D164: Lilly-Protocol/lily-frontend (PR #187: feat(observability): add instrumentation module with onRequestError hook (#111)) | E164: lily-frontend | F164: 75 | G164: 75 | H164: Bounty Revenue | I164: Merged / Settled
A165: 46266 | B165: LILLY-188 | C165: Stellar / Algora | D165: Lilly-Protocol/lily-frontend (PR #188: feat(navigation): add responsive mobile navigation menu to SiteHeader (#118)) | E165: lily-frontend | F165: 75 | G165: 75 | H165: Bounty Revenue | I165: Merged / Settled
A166: 46266 | B166: LILLY-189 | C166: Stellar / Algora | D166: Lilly-Protocol/lily-frontend (PR #189: feat(a11y): add active-route indication with aria-current to SiteHeader and SectionNav (#119)) | E166: lily-frontend | F166: 75 | G166: 75 | H166: Bounty Revenue | I166: Merged / Settled
A167: 46266 | B167: LILLY-191 | C167: Stellar / Algora | D167: Lilly-Protocol/lily-frontend (PR #191: feat(design): add typography scale token set and refactor page-scaffold (#44)) | E167: lily-frontend | F167: 75 | G167: 75 | H167: Bounty Revenue | I167: Merged / Settled
A168: 46267.962 | B168: PERMIFY-3131 | C168: Algora / Stripe | D168: Permify (PR #3131: entity tuple validation regression tests) | E168: 250 | F168: 0 | G168: 250 | H168: Bounty Revenue | I168: Pending Merge
A169: 46267.962 | B169: CAP-SOFTWARE-2207 | C169: Algora / Stripe | D169: CapSoftware (PR #2207: WebRTC session description tests in Chrome extension) | E169: 200 | F169: 0 | G169: 200 | H169: Bounty Revenue | I169: Closed (Unmerged)
A170: 46267.962 | B170: LILLY-STELLAR-326 | C170: Stellar / Algora | D170: Lilly-Protocol (PR #326: Soroban access controller authorization tests) | E170: 250 | F170: 0 | G170: 250 | H170: Bounty Revenue | I170: Pending Merge
A171: 46267.962 | B171: PD-KATANA-1801 | C171: Algora / Stripe | D171: ProjectDiscovery (PR #1801: robotstxt crawler boundary tests in katana) | E171: 200 | F171: 0 | G171: 200 | H171: Bounty Revenue | I171: Pending Merge
A172: 46267.963 | B172: TS-CIRCUIT-1049 | C172: Algora / Stripe | D172: tscircuit (PR #1049: two-pin terminal stub routing tests in schematic solver) | E172: 150 | F172: 0 | G172: 150 | H172: Bounty Revenue | I172: Pending Merge
A173: 46267.967 | B173: PERMIFY-3132 | C173: Algora / Stripe | D173: Permify (PR #3132: entity tuple validation regression tests) | E173: 250 | F173: 0 | G173: 250 | H173: Bounty Revenue | I173: Pending Merge
A174: 46267.967 | B174: CAP-SOFTWARE-2209 | C174: Algora / Stripe | D174: CapSoftware (PR #2209: WebRTC session description tests in Chrome extension) | E174: 200 | F174: 0 | G174: 200 | H174: Bounty Revenue | I174: Closed (Unmerged)
A175: 46267.967 | B175: LILLY-STELLAR-327 | C175: Stellar / Algora | D175: Lilly-Protocol (PR #327: Soroban access controller authorization tests) | E175: 250 | F175: 0 | G175: 250 | H175: Bounty Revenue | I175: Pending Merge
A176: 46267.967 | B176: PD-KATANA-1802 | C176: Algora / Stripe | D176: ProjectDiscovery (PR #1802: robotstxt crawler boundary tests in katana) | E176: 200 | F176: 0 | G176: 200 | H176: Bounty Revenue | I176: Pending Merge
A177: 46267.967 | B177: TS-CIRCUIT-1051 | C177: Algora / Stripe | D177: tscircuit (PR #1051: two-pin terminal stub routing tests in schematic solver) | E177: 150 | F177: 0 | G177: 150 | H177: Bounty Revenue | I177: Pending Merge
A178: 46268.104 | B178: PERMIFY-3133 | C178: Algora / Stripe | D178: Permify (PR #3133: entity tuple validation regression tests) | E178: 250 | F178: 0 | G178: 250 | H178: Bounty Revenue | I178: Pending Merge
A179: 46268.105 | B179: CAP-SOFTWARE-2211 | C179: Algora / Stripe | D179: CapSoftware (PR #2211: WebRTC session description tests in Chrome extension) | E179: 200 | F179: 0 | G179: 200 | H179: Bounty Revenue | I179: Closed (Unmerged)
... A227: 46268 | B227: CHAT-10840 | C227: Algora / Stripe | D227: Chatwoot chatwoot (PR #10840: Conversation webhook dispatch retry & timeout specifications) | E227: 200 | F227: 0 | G227: 200 | H227: Bounty Revenue | I227: In Review
A228: 46270 | B228: TW-25449 | C228: Bounty Contribution | D228: twentyhq/twenty (PR #25449: test(engine): add index definitions comparator edge validation suite) | E228: Operating Revenue | F228: 0 | G228: 250 | H228: Accounts Receivable | I228: Pending Merge
A229: 46270 | B229: PD-KATANA-1808 | C229: Bounty Contribution | D229: projectdiscovery/katana (PR #1808: test(output): add URL sanitization and whitespace boundary tests) | E229: Operating Revenue | F229: 0 | G229: 200 | H229: Accounts Receivable | I229: Pending Merge
A230: 46270 | B230: KEEP-6761 | C230: Bounty Contribution | D230: keephq/keep (PR #6761: test(providers): add provider configuration normalization unit tests) | E230: Operating Revenue | F230: 0 | G230: 200 | H230: Accounts Receivable | I230: Pending Merge
A231: 46270 | B231: CAL-30097 | C231: Bounty Contribution | D231: calcom/cal.diy (PR #30097: test(lib): add event slug coalescing and sanitization specs) | E231: Operating Revenue | F231: 0 | G231: 200 | H231: Accounts Receivable | I231: Pending Merge
A232: 46270 | B232: PERMIFY-3138 | C232: Bounty Contribution | D232: Permify/permify (PR #3138: test(validation): add entity tuple validation regression assertions) | E232: Operating Revenue | F232: 0 | G232: 250 | H232: Accounts Receivable | I232: Pending Merge
A233: 46270 | B233: PD-DNSX-1031 | C233: Opire / Stripe | D233: projectdiscovery/dnsx (PR #1031: test(dnsx): add hostname normalization and trailing dot boundary test suite) | E233: 200 | F233: 0 | G233: 200 | H233: Bounty Revenue | I233: Pending Merge
A234: 46270 | B234: TSC-998 | C234: Opire / Stripe | D234: tscircuit/schematic-trace-solver (PR #1065: test(solver): add net label clearance and route collision avoidance specs) | E234: 250 | F234: 0 | G234: 250 | H234: Bounty Revenue | I234: Pending Merge
A235: 46270 | B235: KEEP-6762 | C235: Opire / Stripe | D235: keephq/keep (PR #6762: test(rules): add alert severity threshold and rule parsing specs) | E235: 200 | F235: 0 | G235: 200 | H235: Bounty Revenue | I235: Pending Merge
A236: 46270 | B236: TW-25450 | C236: Opire / Stripe | D236: twentyhq/twenty (PR #25450: test(metadata): add workspace member role assignment boundary assertions) | E236: 250 | F236: 0 | G236: 250 | H236: Bounty Revenue | I236: Pending Merge
A237: 46270 | B237: LILLY-349 | C237: Opire / Stripe | D237: Lilly-Protocol/lily-contracts (PR #387: test(escrow): add milestone settlement and dispute timeout invariant specs) | E237: 250 | F237: 0 | G237: 250 | H237: Bounty Revenue | I237: Pending Merge
A986: 46270 | B986: AP-15283 | C986: Opire / Stripe | D986: activepieces/activepieces (PR #15283: test(shared): add seek-page pagination utility assertion specs) | E986: 200 | F986: 0 | G986: 200 | H986: Bounty Revenue | I986: Pending Merge
A987: 46270 | B987: PD-SUB-1840 | C987: Opire / Stripe | D987: projectdiscovery/subfinder (PR #1857: test(subfinder): add domain sanitization and wildcard prefix parsing assertions) | E987: 200 | F987: 0 | G987: 200 | H987: Bounty Revenue | I987: Pending Merge
A988: 46270 | B988: TSC-CORE-3650 | C988: Opire / Stripe | D988: tscircuit/core (PR #3662: test(core): add schematic port offset calculations and pin clearance bounds specs) | E988: 250 | F988: 0 | G988: 250 | H988: Bounty Revenue | I988: Pending Merge
A989: 46270 | B989: CAL-30115 | C989: Opire / Stripe | D989: calcom/cal.diy (PR #30098: test(lib): add timezone timestamp normalization and duration coalescing unit tests) | E989: 200 | F989: 0 | G989: 200 | H989: Bounty Revenue | I989: Pending Merge
A990: 46270 | B990: PERMIFY-3145 | C990: Opire / Stripe | D990: Permify/permify (PR #3139: test(validation): add entity tuple namespace formatting and permission identifier assertions) | E990: 250 | F990: 0 | G990: 250 | H990: Bounty Revenue | I990: Pending Merge
A991: 46270 | B991: LILLY-390 | C991: Opire / Stripe | D991: Lilly-Protocol/lily-contracts (PR #388: test(escrow): add milestone basis-point settlement calculation and dispute timeout invariant specs) | E991: 250 | F991: 0 | G991: 250 | H991: Bounty Revenue | I991: Pending Merge
A992: 46270 | B992: KEEP-6790 | C992: Opire / Stripe | D992: keephq/keep (PR #6763: test(rulesengine): add alert severity escalation threshold and fingerprint normalization assertions) | E992: 200 | F992: 0 | G992: 200 | H992: Bounty Revenue | I992: Pending Merge
... A1016: 46270 | B1016: PERMIFY-3190 | C1016: Opire / Stripe | D1016: Permify/permify (PR #3144: test(validation): add graph cycle detection and relation expansion assertions) | E1016: 250 | F1016: 0 | G1016: 250 | H1016: Bounty Revenue | I1016: Pending Merge

Sheet Submissions Log
A1: Date | B1: Organization | C1: Repository | D1: Issue | E1: PR | F1: Feature | G1: Bounty Value | H1: Status | I1: Platform | J1: PR Link
A2: 46259 | B2: Documenso | C2: documenso/documenso | D2: #2844 | E2: #3304 | F2: Atomic Transaction Document Upload Quota | G2: 0 | H2: Closed (Unmerged) | I2: Algora / GitHub | J2: https://github.com/documenso/documenso/pull/3304
A3: 46259 | B3: CapSoftware | C3: CapSoftware/Cap | D3: #1540 | E3: #2145 | F3: Desktop Deeplink Recording Actions Support | G3: 0 | H3: Closed (Unmerged) | I3: Algora / GitHub | J3: https://github.com/CapSoftware/Cap/pull/2145
A4: 46259 | B4: KeepHQ | C4: keephq/keep | D4: #1327 | E4: #6735 | F4: Provider Config Input Validation and Strong Types | G4: 0 | H4: Closed (Unmerged) | I4: Algora / GitHub | J4: https://github.com/keephq/keep/pull/6735
A5: 46260 | B5: Permify | C5: Permify/permify | D5: #1252 | E5: #3096 | F5: Batch Insert in Postgres DataWriter | G5: 0 | H5: Closed (Unmerged) | I5: Algora / GitHub | J5: https://github.com/Permify/permify/pull/3096
A6: 46260 | B6: Documenso | C6: documenso/documenso | D6: #3296 | E6: #3310 | F6: Prevent field from being required and read-only | G6: 100 | H6: In Review | I6: Algora / GitHub | J6: https://github.com/documenso/documenso/pull/3310
A7: 46260 | B7: Capgo | C7: Cap-go/capacitor-updater | D7: #411 | E7: #868 | F7: Support appBoot updateKind for instant bundle application | G7: 100 | H7: In Review | I7: Algora / GitHub | J7: https://github.com/Cap-go/capacitor-updater/pull/868
B8: Twenty | E8: #24635 | G8: 100 | H8: In Review
B9: TSCircuit | E9: #3410 | G9: 100 | H9: In Review
B10: TSCircuit | E10: #477 | G10: 100 | H10: In Review
B11: TSCircuit | E11: #837 | G11: 100 | H11: In Review
B12: Cal.com | E12: #30025 | G12: 100 | H12: In Review
B13: ProjectDiscovery | E13: #1767 | G13: 100 | H13: In Review
B14: ProjectDiscovery | E14: #1766 | G14: 100 | H14: In Review
B15: ProjectDiscovery | E15: #1017 | G15: 100 | H15: In Review
B16: ProjectDiscovery | E16: #1016 | G16: 100 | H16: In Review
B17: Claude Builders | E17: #3760 | G17: 115 | H17: In Review
B18: Claude Builders | E18: #3758 | G18: 115 | H18: In Review
B19: Claude Builders | E19: #3741 | G19: 115 | H19: In Review
... B23: Twenty | E23: #24712 | G23: 0 | H23: Closed (Unmerged)
A24: 46261 | B24: Lilly-Protocol | C24: Lilly-Protocol/lily-frontend | D24: #96 | E24: #178 | F24: Starter SVGs & Quick Start Cards | G24: 100 | H24: In Review | I24: Algora / GitHub | J24: https://github.com/Lilly-Protocol/lily-frontend/pull/178
A25: 46261 | B25: Lilly-Protocol | C25: Lilly-Protocol/lily-frontend | D25: #110 | E25: #180 | F25: Security Headers & CSP Configuration | G25: 75 | H25: In Review | I25: Algora / GitHub | J25: https://github.com/Lilly-Protocol/lily-frontend/pull/180
A26: 46261 | B26: Lilly-Protocol | C26: Lilly-Protocol/lily-backend | D26: #143 | E26: #227 | F26: Test Coverage Thresholds & Scripts | G26: 50 | H26: In Review | I26: Algora / GitHub | J26: https://github.com/Lilly-Protocol/lily-backend/pull/227
A27: 46261 | B27: Lilly-Protocol | C27: Lilly-Protocol/lily-frontend | D27: #125 | E27: #181 | F27: (New Feature) | G27: 70 | H27: In Review | I27: Algora / GitHub | J27: https://github.com/Lilly-Protocol/lily-frontend/pull/181
A28: 46261 | B28: Lilly-Protocol | C28: Lilly-Protocol/lily-frontend | D28: #113 | E28: #182 | F28: Add accessible responsive timeline component | G28: 75 | H28: In Review | I28: Algora / GitHub | J28: https://github.com/Lilly-Protocol/lily-frontend/pull/182
A29: 46261 | B29: Lilly-Protocol | C29: lily-frontend | D29: #96 | E29: #178 | F29: Remove Starter SVGs | G29: 100 | H29: In Review | I29: GitHub
A30: 46261 | B30: Lilly-Protocol | C30: lily-frontend | D30: #110 | E30: #180 | F30: Security Headers | G30: 75 | H30: In Review | I30: GitHub
A31: 46261 | B31: Lilly-Protocol | C31: lily-backend | D31: #143 | E31: #227 | F31: Coverage Thresholds | G31: 50 | H31: In Review | I31: GitHub
A32: 46261 | B32: Lilly-Protocol | C32: lily-frontend | D32: #125 | E32: #181 | F32: Request ID Middleware | G32: 70 | H32: In Review | I32: GitHub
A33: 46261 | B33: Lilly-Protocol | C33: lily-frontend | D33: #113 | E33: #182 | F33: Timeline Component | G33: 75 | H33: In Review | I33: GitHub
A34: 46261 | B34: Lilly-Protocol | C34: lily-frontend | D34: #121 | E34: #183 | F34: App Icon Routes | G34: 60 | H34: In Review | I34: GitHub
A35: 46261 | B35: Lilly-Protocol | C35: lily-frontend | D35: #46 | E35: #184 | F35: Elevation & Shadow Scale | G35: 75 | H35: In Review | I35: GitHub
A36: 46261 | B36: Lilly-Protocol | C36: lily-frontend | D36: LILY-96 | E36: #178 | F36: lily-frontend #96 | G36: 100 | H36: Open | I36: Algora / GitHub | J36: https://github.com/Lilly-Protocol/lily-frontend/pull/178
A37: 46261 | B37: Lilly-Protocol | C37: lily-frontend | D37: LILY-110 | E37: #180 | F37: lily-frontend #110 | G37: 75 | H37: Open | I37: Algora / GitHub | J37: https://github.com/Lilly-Protocol/lily-frontend/pull/180
A38: 46261 | B38: Lilly-Protocol | C38: lily-backend | D38: LILY-143 | E38: #227 | F38: lily-backend #143 | G38: 50 | H38: Open | I38: Algora / GitHub | J38: https://github.com/Lilly-Protocol/lily-backend/pull/227
A39: 46261 | B39: Lilly-Protocol | C39: lily-frontend | D39: LILY-125 | E39: #181 | F39: lily-frontend #125 | G39: 70 | H39: Open | I39: Algora / GitHub | J39: https://github.com/Lilly-Protocol/lily-frontend/pull/181
A40: 46261 | B40: Lilly-Protocol | C40: lily-frontend | D40: LILY-113 | E40: #182 | F40: lily-frontend #113 | G40: 75 | H40: Open | I40: Algora / GitHub | J40: https://github.com/Lilly-Protocol/lily-frontend/pull/182
A41: 46261 | B41: Lilly-Protocol | C41: lily-frontend | D41: LILY-121 | E41: #183 | F41: lily-frontend #121 | G41: 60 | H41: Open | I41: Algora / GitHub | J41: https://github.com/Lilly-Protocol/lily-frontend/pull/183
A42: 46261 | B42: Lilly-Protocol | C42: lily-frontend | D42: LILY-46 | E42: #184 | F42: lily-frontend #46 | G42: 75 | H42: Open | I42: Algora / GitHub | J42: https://github.com/Lilly-Protocol/lily-frontend/pull/184
A43: 46261 | B43: Lilly-Protocol | C43: lily-frontend | D43: LILY-30 | E43: #185 | F43: lily-frontend #30 | G43: 75 | H43: Open | I43: Algora / GitHub | J43: https://github.com/Lilly-Protocol/lily-frontend/pull/185
A44: 46261 | B44: Lilly-Protocol | C44: lily-frontend | D44: LILY-47 | E44: #186 | F44: lily-frontend #47 | G44: 75 | H44: Open | I44: Algora / GitHub | J44: https://github.com/Lilly-Protocol/lily-frontend/pull/186
A45: 46261 | B45: Lilly-Protocol | C45: Lilly-Protocol/lily-frontend | D45: #30 | E45: #185 | F45: test(a11y): add axe accessibility assertions to component tests (#30) | G45: 75 | H45: In Review | I45: Algora / GitHub | J45: https://github.com/Lilly-Protocol/lily-frontend/pull/185
A46: 46261 | B46: Lilly-Protocol | C46: Lilly-Protocol/lily-frontend | D46: #96 | E46: PR #178 | F46: Remove Starter SVGs | G46: 100 | H46: In Review | I46: Algora / GitHub | J46: https://github.com/Lilly-Protocol/lily-frontend/pull/178
A47: 46261 | B47: Lilly-Protocol | C47: Lilly-Protocol/lily-frontend | D47: #110 | E47: PR #180 | F47: Security Headers | G47: 75 | H47: In Review | I47: Algora / GitHub | J47: https://github.com/Lilly-Protocol/lily-frontend/pull/180
... A66: 46261 | B66: OphirPay | C66: OphirPay/OphirPay | D66: #397 | E66: #417 | F66: Memo Sanitization & XSS | G66: 200 | H66: In Review | I66: Algora / GitHub | J66: https://github.com/OphirPay/OphirPay/pull/417
A67: 46261 | B67: OphirPay | C67: OphirPay/OphirPay | E67: #417 | F67: OphirPay PR #417 | G67: 200 | H67: In Review | I67: GitHub | J67: https://github.com/OphirPay/OphirPay/pull/417
A68: 46261 | B68: Lilly-Protocol | C68: Lilly-Protocol/lily-frontend | E68: #178 | F68: lily-frontend PR #178 | G68: 100 | H68: In Review | I68: GitHub | J68: https://github.com/Lilly-Protocol/lily-frontend/pull/178
A69: 46261 | B69: Lilly-Protocol | C69: Lilly-Protocol/lily-frontend | E69: #180 | F69: lily-frontend PR #180 | G69: 75 | H69: In Review | I69: GitHub | J69: https://github.com/Lilly-Protocol/lily-frontend/pull/180
A70: 46261 | B70: Lilly-Protocol | C70: Lilly-Protocol/lily-backend | E70: #227 | F70: lily-backend PR #227 | G70: 50 | H70: In Review | I70: GitHub | J70: https://github.com/Lilly-Protocol/lily-backend/pull/227
A71: 46261 | B71: Lilly-Protocol | C71: Lilly-Protocol/lily-frontend | E71: #181 | F71: lily-frontend PR #181 | G71: 70 | H71: In Review | I71: GitHub | J71: https://github.com/Lilly-Protocol/lily-frontend/pull/181
A72: 46261 | B72: Lilly-Protocol | C72: Lilly-Protocol/lily-frontend | E72: #182 | F72: lily-frontend PR #182 | G72: 75 | H72: In Review | I72: GitHub | J72: https://github.com/Lilly-Protocol/lily-frontend/pull/182
A73: 46261 | B73: Lilly-Protocol | C73: Lilly-Protocol/lily-frontend | E73: #183 | F73: lily-frontend PR #183 | G73: 60 | H73: In Review | I73: GitHub | J73: https://github.com/Lilly-Protocol/lily-frontend/pull/183
A74: 46261 | B74: Lilly-Protocol | C74: Lilly-Protocol/lily-frontend | E74: #184 | F74: lily-frontend PR #184 | G74: 75 | H74: In Review | I74: GitHub | J74: https://github.com/Lilly-Protocol/lily-frontend/pull/184
A75: 46261 | B75: Lilly-Protocol | C75: Lilly-Protocol/lily-frontend | E75: #185 | F75: lily-frontend PR #185 | G75: 75 | H75: In Review | I75: GitHub | J75: https://github.com/Lilly-Protocol/lily-frontend/pull/185
A76: 46261 | B76: Lilly-Protocol | C76: Lilly-Protocol/lily-frontend | E76: #186 | F76: lily-frontend PR #186 | G76: 75 | H76: In Review | I76: GitHub | J76: https://github.com/Lilly-Protocol/lily-frontend/pull/186
A77: 46261 | B77: Lilly-Protocol | C77: Lilly-Protocol/lily-frontend | E77: #187 | F77: lily-frontend PR #187 | G77: 35 | H77: In Review | I77: GitHub | J77: https://github.com/Lilly-Protocol/lily-frontend/pull/187
A78: 45589 | B78: Lilly-Protocol | C78: repo | D78: issue | E78: pr | F78: feature | G78: 90 | H78: Pending | I78: GitHub | J78: link
A79: 45589 | B79: Lilly-Protocol | C79: repo | D79: issue | E79: pr | F79: feature | G79: 90 | H79: Pending | I79: GitHub | J79: link
A80: 45589 | B80: Lilly-Protocol | C80: repo | D80: issue | E80: pr | F80: feature | G80: 90 | H80: Pending | I80: GitHub | J80: link
A81: 45589 | B81: Lilly-Protocol | C81: repo | D81: issue | E81: pr | F81: feature | G81: 90 | H81: Pending | I81: GitHub | J81: link
A82: 45589 | B82: Lilly-Protocol | C82: repo | D82: issue | E82: pr | F82: feature | G82: 90 | H82: Pending | I82: GitHub | J82: link
A83: 45589 | B83: Lilly-Protocol | C83: repo | D83: issue | E83: pr | F83: feature | G83: 90 | H83: Pending | I83: GitHub | J83: link
A84: 45589 | B84: Lilly-Protocol | C84: repo | D84: issue | E84: pr | F84: feature | G84: 90 | H84: Pending | I84: GitHub | J84: link
A85: 45589 | B85: OphirPay | C85: repo | D85: issue | E85: pr | F85: feature | G85: 90 | H85: Pending | I85: GitHub | J85: link
A86: 45589 | B86: OphirPay | C86: repo | D86: issue | E86: pr | F86: feature | G86: 90 | H86: Pending | I86: GitHub | J86: link
A87: 45589 | B87: OphirPay | C87: repo | D87: issue | E87: pr | F87: feature | G87: 90 | H87: Pending | I87: GitHub | J87: link
A88: 45589 | B88: OphirPay | C88: repo | D88: issue | E88: pr | F88: feature | G88: 90 | H88: Pending | I88: GitHub | J88: link
A89: 45589 | B89: OphirPay | C89: repo | D89: issue | E89: pr | F89: feature | G89: 100 | H89: Pending | I89: GitHub | J89: link
A90: 46261 | B90: OphirPay | C90: ophirpay/ophirpay | D90: #396 | F90: Wallet Auth Rate Limiting | G90: 200 | H90: In Review | I90: Algora / GitHub
A91: 46261 | B91: OphirPay | C91: ophirpay/ophirpay | D91: #406 | F91: CI Playwright Matrix Sharding | G91: 200 | H91: In Review | I91: Algora / GitHub
A92: 46261 | B92: OphirPay | C92: ophirpay/ophirpay | D92: #401 | F92: Mainnet Deployment Runbook | G92: 200 | H92: In Review | I92: Algora / GitHub
A93: 46261 | B93: OphirPay | C93: ophirpay/ophirpay | D93: #400 | F93: Contributing & Bounty Guide | G93: 200 | H93: In Review | I93: Algora / GitHub
A94: 46261 | B94: Lily | C94: lily-app/lily-frontend | D94: #118 | F94: Responsive Mobile Nav Menu | G94: 30 | H94: In Review | I94: Algora / GitHub
A95: 46261 | B95: Lily | C95: lily-app/lily-frontend | D95: #119 | F95: Active Route aria-current | G95: 25 | H95: In Review | I95: Algora / GitHub
A96: 46261 | B96: Lily | C96: lily-app/lily-frontend | D96: #112 | F96: Shared Site Footer | G96: 20 | H96: In Review | I96: Algora / GitHub
A97: 46261 | B97: Lily | C97: lily-app/lily-frontend | D97: #44 | F97: Typography Scale Tokens | G97: 90 | H97: In Review | I97: Algora / GitHub
B98: Exo | C98: Distributed Inference | E98: #283 | F98: Multi-Model Fix | G98: 500 | H98: Verified | I98: Algora
B99: Twenty CRM | C99: Workflow Engine | E99: #1105 | F99: Graph Task Fix | G99: 350 | H99: Verified | I99: Algora
B100: Cal.com | C100: Scheduling Routing | E100: #5291 | F100: Slot Timezone Fix | G100: 300 | H100: Verified | I100: Algora
B101: Lily Protocol | C101: Soroban Payments | E101: #14 | F101: Soroban Auth Fix | G101: 300 | H101: Verified | I101: Stellar
B102: Documenso | C102: PDF Sign Logic | E102: #412 | F102: Hash Signature | G102: 250 | H102: Verified | I102: Algora
B103: Cap | C103: Chrome Extension | E103: #88 | F103: Tab Audio Stream | G103: 200 | H103: Verified | I103: Algora
B104: TSCircuit | C104: schematic-trace | E104: #82 | F104: Label Solver Bounds | G104: 150 | H104: Verified | I104: Algora
B105: ProjectDiscovery | C105: dnsx | E105: #940 | F105: CLI Stream Output | G105: 100 | H105: Verified | I105: Algora
